{
    "pump": [],
    "thermostat": [
        17,
        18,
        28
    ],
    "fan": [],
    "dehumidification": [],
    "thermostat_ui": [],
    "smartenergy_metering": [],
    "generic_tunnel": [],
    "bacnet_regular_analog_input": [],
    "bacnet_extended_analog_input": [],
    "bacnet_regular_analog_output": [],
    "bacnet_extended_analog_output": [],
    "bacnet_regular_analog_value": [],
    "bacnet_extended_analog_value": [],
    "bacnet_regular_binary_input": [],
    "bacnet_extended_binary_input": [],
    "bacnet_regular_binary_output": [],
    "bacnet_extended_binary_output": [],
    "bacnet_regular_binary_value": [],
    "bacnet_extended_binary_value": [],
    "bacnet_regular_multistate_input": [],
    "bacnet_extended_multistate_input": [],
    "bacnet_regular_multistate_output": [],
    "bacnet_extended_multistate_output": [],
    "bacnet_regular_multistate_value": [],
    "bacnet_extended_multistate_value": [],
    "appliance_id": [],
    "meter_id": [],
    "appliance_event": [],
    "appliance_stats": [],
    "electrical_measurement": [],
    "diagnostic": [],
    "shade": [],
    "door_lock": [],
    "window_covering": [
        8,
        9
    ],
    "basic": [],
    "power": [],
    "device_temperature": [],
    "identify": [],
    "groups": [],
    "scenes": [],
    "on_off": [
        0
    ],
    "on_off_config": [],
    "level": [
        0,
        4
    ],
    "alarms": [],
    "time": [],
    "rssi_location": [],
    "analog_input": [],
    "analog_output": [],
    "analog_value": [],
    "binary_input": [],
    "binary_output": [],
    "binary_value": [],
    "multistate_input": [],
    "multistate_output": [],
    "multistate_value": [],
    "commissioning": [],
    "partition": [],
    "ota": [],
    "power_profile": [],
    "appliance_control": [],
    "poll_control": [],
    "keep_alive": [],
    "ias_zone": [],
    "ias_ace": [],
    "ias_wd": [],
    "illuminance": [],
    "illuminance_level": [],
    "temperature": [],
    "pressure": [],
    "flow": [],
    "humidity": [],
    "occupancy": [],
    "leaf_wetness": [],
    "soil_moisture": [],
    "ph": [],
    "electrical_conductivity": [],
    "wind_speed": [],
    "light_color": [
        1,
        3,
        4,
        7,
        16384,
        16386,
        16387,
        16388
    ],
    "light_ballast": []
}